.gitignore
.gitlab-ci.yml
README.md
setup.py
bin/lbCVMFSchecker
lbCVMFSchecker/LbCVMFSCheckerPluginBase.py
lbCVMFSchecker/LbCvmfsChecker.py
lbCVMFSchecker/LbDBConnector.py
lbCVMFSchecker/LbEmailer.py
lbCVMFSchecker/PluginLoader.py
lbCVMFSchecker/PluginManager.py
lbCVMFSchecker/__init__.py
lbCVMFSchecker.egg-info/PKG-INFO
lbCVMFSchecker.egg-info/SOURCES.txt
lbCVMFSchecker.egg-info/dependency_links.txt
lbCVMFSchecker.egg-info/requires.txt
lbCVMFSchecker.egg-info/top_level.txt
lbCVMFSchecker/Plugins/CVMFSync.py
lbCVMFSchecker/Plugins/LogChecker.py
lbCVMFSchecker/Plugins/NightliesChecker.py
lbCVMFSchecker/Plugins/NightliesErrorsChecker.py
lbCVMFSchecker/Plugins/NightliesRemove.py
lbCVMFSchecker/Plugins/ZZZAlivePlugin.py
lbCVMFSchecker/Plugins/__init__.py
lbCVMFSchecker/Plugins/tests/TestCVMFSync.py
lbCVMFSchecker/Plugins/tests/TestLogChckerPlugin.py
lbCVMFSchecker/Plugins/tests/TestNightliesPlugin.py
lbCVMFSchecker/Plugins/tests/__init__.py
lbCVMFSchecker/tests/MockLogger.py
lbCVMFSchecker/tests/TestDBConnector.py
lbCVMFSchecker/tests/TestEmailer.py
lbCVMFSchecker/tests/TestPluginBase.py
lbCVMFSchecker/tests/TestPluginLoader.py
lbCVMFSchecker/tests/TestPluginManager.py
lbCVMFSchecker/tests/__init__.py
lbCVMFSchecker/tests/Plugins/MockPlugin.py
lbCVMFSchecker/tests/Plugins/__init__.py