Metadata-Version: 1.1
Name: lbCVMFSchecker
Version: 1.0.8
Summary: LHCb CVMFS-Stratum0 checker tool
Home-page: https://gitlab.cern.ch/lhcb-core/cvmfs-stratum0-checker
Author: CERN - LHCb Core Software
Author-email: lhcb-core-soft@cern.ch
License: GPL
Keywords: LHCb
Platform: UNKNOWN
Classifier: Development Status :: 3 - Alpha
Classifier: License :: OSI Approved :: GNU General Public License v3 (GPLv3)
Classifier: Programming Language :: Python :: 2.6
Classifier: Programming Language :: Python :: 2.7
Classifier: Programming Language :: Python :: 3.5
